{
  "player_id": "nfl_3d255e0a4a3e",
  "player_name": "Luke Wysong",
  "position": "WR",
  "team_id": "MIN",
  "team": "MIN",
  "school": "",
  "league": "NFL",
  "level": "Pro",
  "age": "",
  "height": 70.0,
  "weight": 186.0,
  "source": "nflreadpy",
  "source_confidence": "Medium",
  "ares_score": "Premium",
  "market_score": "Premium",
  "value_tier": "Premium",
  "trend": "Premium",
  "confidence": "Premium",
  "has_nfl_detail": false,
  "nfl_detail_url": "",
  "is_placeholder": false,
  "premium_locked": true
}