{
  "player_id": "nfl_9eb559664395",
  "player_name": "Baron Browning",
  "position": "LB",
  "team_id": "ARI",
  "team": "ARI",
  "school": "",
  "league": "NFL",
  "level": "Pro",
  "age": 27.0,
  "height": 75.0,
  "weight": 255.0,
  "source": "nflreadpy",
  "source_confidence": "Medium",
  "ares_score": "Premium",
  "market_score": "Premium",
  "value_tier": "Premium",
  "trend": "Premium",
  "confidence": "Premium",
  "has_nfl_detail": false,
  "nfl_detail_url": "",
  "is_placeholder": false,
  "premium_locked": true
}