{
  "player": {
    "player_name": "Mike Morris",
    "position": "DE",
    "level": "Pro",
    "team_id": "SEA",
    "team": "SEA",
    "school": "",
    "league": "NFL",
    "age": 25.0,
    "height": 78.0,
    "weight": 306.0,
    "source": "nflreadpy",
    "source_player_id": "CB|M.Morris|SEA",
    "source_confidence": "Medium",
    "is_placeholder": false,
    "player_id": "nfl_54d0fa76e9a9"
  },
  "season_summary": [
    {
      "season": 2025,
      "passing_yards": 0,
      "passing_tds": 0,
      "passing_interceptions": 0,
      "rushing_yards": 0,
      "rushing_tds": 0,
      "receptions": 0,
      "targets": 0,
      "receiving_yards": 0,
      "receiving_tds": 0,
      "def_tackles": 22,
      "def_sacks": 0.0,
      "def_interceptions": 0,
      "fantasy_points_ppr": 0.0
    },
    {
      "season": 2024,
      "passing_yards": 0,
      "passing_tds": 0,
      "passing_interceptions": 0,
      "rushing_yards": 0,
      "rushing_tds": 0,
      "receptions": 0,
      "targets": 0,
      "receiving_yards": 0,
      "receiving_tds": 0,
      "def_tackles": 5,
      "def_sacks": 0.0,
      "def_interceptions": 0,
      "fantasy_points_ppr": 0.0
    },
    {
      "season": 2023,
      "passing_yards": 0,
      "passing_tds": 0,
      "passing_interceptions": 0,
      "rushing_yards": 0,
      "rushing_tds": 0,
      "receptions": 0,
      "targets": 0,
      "receiving_yards": 0,
      "receiving_tds": 0,
      "def_tackles": 3,
      "def_sacks": 0.0,
      "def_interceptions": 0,
      "fantasy_points_ppr": 0.0
    },
    {
      "season": 2008,
      "passing_yards": 0,
      "passing_tds": 0,
      "passing_interceptions": 0,
      "rushing_yards": 574,
      "rushing_tds": 0,
      "receptions": 19,
      "targets": 0,
      "receiving_yards": 136,
      "receiving_tds": 2,
      "def_tackles": 3,
      "def_sacks": 0.0,
      "def_interceptions": 0,
      "fantasy_points_ppr": 100.0
    },
    {
      "season": 2007,
      "passing_yards": 0,
      "passing_tds": 0,
      "passing_interceptions": 0,
      "rushing_yards": 640,
      "rushing_tds": 4,
      "receptions": 23,
      "targets": 0,
      "receiving_yards": 213,
      "receiving_tds": 1,
      "def_tackles": 3,
      "def_sacks": 0.0,
      "def_interceptions": 0,
      "fantasy_points_ppr": 136.3
    },
    {
      "season": 2006,
      "passing_yards": 0,
      "passing_tds": 0,
      "passing_interceptions": 0,
      "rushing_yards": 627,
      "rushing_tds": 0,
      "receptions": 11,
      "targets": 0,
      "receiving_yards": 46,
      "receiving_tds": 0,
      "def_tackles": 1,
      "def_sacks": 0.0,
      "def_interceptions": 0,
      "fantasy_points_ppr": 76.3
    },
    {
      "season": 2005,
      "passing_yards": 0,
      "passing_tds": 0,
      "passing_interceptions": 0,
      "rushing_yards": 361,
      "rushing_tds": 1,
      "receptions": 7,
      "targets": 0,
      "receiving_yards": 70,
      "receiving_tds": 0,
      "def_tackles": 8,
      "def_sacks": 0.0,
      "def_interceptions": 0,
      "fantasy_points_ppr": 56.1
    },
    {
      "season": 2004,
      "passing_yards": 0,
      "passing_tds": 0,
      "passing_interceptions": 0,
      "rushing_yards": 135,
      "rushing_tds": 0,
      "receptions": 9,
      "targets": 0,
      "receiving_yards": 53,
      "receiving_tds": 0,
      "def_tackles": 5,
      "def_sacks": 0.0,
      "def_interceptions": 0,
      "fantasy_points_ppr": 27.8
    },
    {
      "season": 2003,
      "passing_yards": 0,
      "passing_tds": 0,
      "passing_interceptions": 0,
      "rushing_yards": 243,
      "rushing_tds": 0,
      "receptions": 4,
      "targets": 0,
      "receiving_yards": 32,
      "receiving_tds": 1,
      "def_tackles": 3,
      "def_sacks": 0.0,
      "def_interceptions": 0,
      "fantasy_points_ppr": 37.5
    },
    {
      "season": 2002,
      "passing_yards": 0,
      "passing_tds": 0,
      "passing_interceptions": 0,
      "rushing_yards": 153,
      "rushing_tds": 0,
      "receptions": 3,
      "targets": 3,
      "receiving_yards": 25,
      "receiving_tds": 0,
      "def_tackles": 3,
      "def_sacks": 0.0,
      "def_interceptions": 0,
      "fantasy_points_ppr": 24.8
    }
  ],
  "weekly_recent": [
    {
      "season": 2025,
      "week": 21,
      "team": "SEA",
      "opponent": "LA",
      "passing_yards": 0,
      "passing_tds": 0,
      "passing_interceptions": 0,
      "rushing_yards": 0,
      "rushing_tds": 0,
      "receptions": 0,
      "targets": 0,
      "receiving_yards": 0,
      "receiving_tds": 0,
      "def_tackles": 1,
      "def_sacks": 0.0,
      "def_interceptions": 0,
      "fantasy_points_ppr": 0.0
    },
    {
      "season": 2025,
      "week": 20,
      "team": "SEA",
      "opponent": "SF",
      "passing_yards": 0,
      "passing_tds": 0,
      "passing_interceptions": 0,
      "rushing_yards": 0,
      "rushing_tds": 0,
      "receptions": 0,
      "targets": 0,
      "receiving_yards": 0,
      "receiving_tds": 0,
      "def_tackles": 3,
      "def_sacks": 0.0,
      "def_interceptions": 0,
      "fantasy_points_ppr": 0.0
    },
    {
      "season": 2025,
      "week": 18,
      "team": "SEA",
      "opponent": "SF",
      "passing_yards": 0,
      "passing_tds": 0,
      "passing_interceptions": 0,
      "rushing_yards": 0,
      "rushing_tds": 0,
      "receptions": 0,
      "targets": 0,
      "receiving_yards": 0,
      "receiving_tds": 0,
      "def_tackles": 1,
      "def_sacks": 0.0,
      "def_interceptions": 0,
      "fantasy_points_ppr": 0.0
    },
    {
      "season": 2025,
      "week": 17,
      "team": "SEA",
      "opponent": "CAR",
      "passing_yards": 0,
      "passing_tds": 0,
      "passing_interceptions": 0,
      "rushing_yards": 0,
      "rushing_tds": 0,
      "receptions": 0,
      "targets": 0,
      "receiving_yards": 0,
      "receiving_tds": 0,
      "def_tackles": 2,
      "def_sacks": 0.0,
      "def_interceptions": 0,
      "fantasy_points_ppr": 0.0
    },
    {
      "season": 2025,
      "week": 14,
      "team": "SEA",
      "opponent": "ATL",
      "passing_yards": 0,
      "passing_tds": 0,
      "passing_interceptions": 0,
      "rushing_yards": 0,
      "rushing_tds": 0,
      "receptions": 0,
      "targets": 0,
      "receiving_yards": 0,
      "receiving_tds": 0,
      "def_tackles": 0,
      "def_sacks": 0.0,
      "def_interceptions": 0,
      "fantasy_points_ppr": 0.0
    },
    {
      "season": 2025,
      "week": 12,
      "team": "SEA",
      "opponent": "TEN",
      "passing_yards": 0,
      "passing_tds": 0,
      "passing_interceptions": 0,
      "rushing_yards": 0,
      "rushing_tds": 0,
      "receptions": 0,
      "targets": 0,
      "receiving_yards": 0,
      "receiving_tds": 0,
      "def_tackles": 0,
      "def_sacks": 0.0,
      "def_interceptions": 0,
      "fantasy_points_ppr": 0.0
    },
    {
      "season": 2025,
      "week": 11,
      "team": "SEA",
      "opponent": "LA",
      "passing_yards": 0,
      "passing_tds": 0,
      "passing_interceptions": 0,
      "rushing_yards": 0,
      "rushing_tds": 0,
      "receptions": 0,
      "targets": 0,
      "receiving_yards": 0,
      "receiving_tds": 0,
      "def_tackles": 1,
      "def_sacks": 0.0,
      "def_interceptions": 0,
      "fantasy_points_ppr": 0.0
    },
    {
      "season": 2025,
      "week": 10,
      "team": "SEA",
      "opponent": "ARI",
      "passing_yards": 0,
      "passing_tds": 0,
      "passing_interceptions": 0,
      "rushing_yards": 0,
      "rushing_tds": 0,
      "receptions": 0,
      "targets": 0,
      "receiving_yards": 0,
      "receiving_tds": 0,
      "def_tackles": 2,
      "def_sacks": 0.0,
      "def_interceptions": 0,
      "fantasy_points_ppr": 0.0
    },
    {
      "season": 2025,
      "week": 9,
      "team": "SEA",
      "opponent": "WAS",
      "passing_yards": 0,
      "passing_tds": 0,
      "passing_interceptions": 0,
      "rushing_yards": 0,
      "rushing_tds": 0,
      "receptions": 0,
      "targets": 0,
      "receiving_yards": 0,
      "receiving_tds": 0,
      "def_tackles": 3,
      "def_sacks": 0.0,
      "def_interceptions": 0,
      "fantasy_points_ppr": 0.0
    },
    {
      "season": 2025,
      "week": 7,
      "team": "SEA",
      "opponent": "HOU",
      "passing_yards": 0,
      "passing_tds": 0,
      "passing_interceptions": 0,
      "rushing_yards": 0,
      "rushing_tds": 0,
      "receptions": 0,
      "targets": 0,
      "receiving_yards": 0,
      "receiving_tds": 0,
      "def_tackles": 1,
      "def_sacks": 0.0,
      "def_interceptions": 0,
      "fantasy_points_ppr": 0.0
    },
    {
      "season": 2025,
      "week": 6,
      "team": "SEA",
      "opponent": "JAX",
      "passing_yards": 0,
      "passing_tds": 0,
      "passing_interceptions": 0,
      "rushing_yards": 0,
      "rushing_tds": 0,
      "receptions": 0,
      "targets": 0,
      "receiving_yards": 0,
      "receiving_tds": 0,
      "def_tackles": 1,
      "def_sacks": 0.0,
      "def_interceptions": 0,
      "fantasy_points_ppr": 0.0
    },
    {
      "season": 2025,
      "week": 3,
      "team": "SEA",
      "opponent": "NO",
      "passing_yards": 0,
      "passing_tds": 0,
      "passing_interceptions": 0,
      "rushing_yards": 0,
      "rushing_tds": 0,
      "receptions": 0,
      "targets": 0,
      "receiving_yards": 0,
      "receiving_tds": 0,
      "def_tackles": 5,
      "def_sacks": 0.0,
      "def_interceptions": 0,
      "fantasy_points_ppr": 0.0
    },
    {
      "season": 2025,
      "week": 2,
      "team": "SEA",
      "opponent": "PIT",
      "passing_yards": 0,
      "passing_tds": 0,
      "passing_interceptions": 0,
      "rushing_yards": 0,
      "rushing_tds": 0,
      "receptions": 0,
      "targets": 0,
      "receiving_yards": 0,
      "receiving_tds": 0,
      "def_tackles": 2,
      "def_sacks": 0.0,
      "def_interceptions": 0,
      "fantasy_points_ppr": 0.0
    },
    {
      "season": 2024,
      "week": 9,
      "team": "SEA",
      "opponent": "LA",
      "passing_yards": 0,
      "passing_tds": 0,
      "passing_interceptions": 0,
      "rushing_yards": 0,
      "rushing_tds": 0,
      "receptions": 0,
      "targets": 0,
      "receiving_yards": 0,
      "receiving_tds": 0,
      "def_tackles": 1,
      "def_sacks": 0.0,
      "def_interceptions": 0,
      "fantasy_points_ppr": 0.0
    },
    {
      "season": 2024,
      "week": 3,
      "team": "SEA",
      "opponent": "MIA",
      "passing_yards": 0,
      "passing_tds": 0,
      "passing_interceptions": 0,
      "rushing_yards": 0,
      "rushing_tds": 0,
      "receptions": 0,
      "targets": 0,
      "receiving_yards": 0,
      "receiving_tds": 0,
      "def_tackles": 2,
      "def_sacks": 0.0,
      "def_interceptions": 0,
      "fantasy_points_ppr": 0.0
    },
    {
      "season": 2024,
      "week": 1,
      "team": "SEA",
      "opponent": "DEN",
      "passing_yards": 0,
      "passing_tds": 0,
      "passing_interceptions": 0,
      "rushing_yards": 0,
      "rushing_tds": 0,
      "receptions": 0,
      "targets": 0,
      "receiving_yards": 0,
      "receiving_tds": 0,
      "def_tackles": 2,
      "def_sacks": 0.0,
      "def_interceptions": 0,
      "fantasy_points_ppr": 0.0
    },
    {
      "season": 2023,
      "week": 1,
      "team": "SEA",
      "opponent": "LA",
      "passing_yards": 0,
      "passing_tds": 0,
      "passing_interceptions": 0,
      "rushing_yards": 0,
      "rushing_tds": 0,
      "receptions": 0,
      "targets": 0,
      "receiving_yards": 0,
      "receiving_tds": 0,
      "def_tackles": 3,
      "def_sacks": 0.0,
      "def_interceptions": 0,
      "fantasy_points_ppr": 0.0
    },
    {
      "season": 2008,
      "week": 17,
      "team": "SEA",
      "opponent": "ARI",
      "passing_yards": 0,
      "passing_tds": 0,
      "passing_interceptions": 0,
      "rushing_yards": 45,
      "rushing_tds": 0,
      "receptions": 3,
      "targets": 0,
      "receiving_yards": 26,
      "receiving_tds": 0,
      "def_tackles": 0,
      "def_sacks": 0.0,
      "def_interceptions": 0,
      "fantasy_points_ppr": 8.1
    },
    {
      "season": 2008,
      "week": 16,
      "team": "SEA",
      "opponent": "NYJ",
      "passing_yards": 0,
      "passing_tds": 0,
      "passing_interceptions": 0,
      "rushing_yards": 116,
      "rushing_tds": 0,
      "receptions": 0,
      "targets": 0,
      "receiving_yards": 0,
      "receiving_tds": 0,
      "def_tackles": 0,
      "def_sacks": 0.0,
      "def_interceptions": 0,
      "fantasy_points_ppr": 11.6
    },
    {
      "season": 2008,
      "week": 15,
      "team": "SEA",
      "opponent": "LA",
      "passing_yards": 0,
      "passing_tds": 0,
      "passing_interceptions": 0,
      "rushing_yards": 86,
      "rushing_tds": 0,
      "receptions": 0,
      "targets": 0,
      "receiving_yards": 0,
      "receiving_tds": 0,
      "def_tackles": 0,
      "def_sacks": 0.0,
      "def_interceptions": 0,
      "fantasy_points_ppr": 8.6
    },
    {
      "season": 2008,
      "week": 14,
      "team": "SEA",
      "opponent": "NE",
      "passing_yards": 0,
      "passing_tds": 0,
      "passing_interceptions": 0,
      "rushing_yards": 39,
      "rushing_tds": 0,
      "receptions": 2,
      "targets": 0,
      "receiving_yards": 19,
      "receiving_tds": 0,
      "def_tackles": 0,
      "def_sacks": 0.0,
      "def_interceptions": 0,
      "fantasy_points_ppr": 7.8
    },
    {
      "season": 2008,
      "week": 13,
      "team": "SEA",
      "opponent": "DAL",
      "passing_yards": 0,
      "passing_tds": 0,
      "passing_interceptions": 0,
      "rushing_yards": 10,
      "rushing_tds": 0,
      "receptions": 3,
      "targets": 0,
      "receiving_yards": 23,
      "receiving_tds": 0,
      "def_tackles": 0,
      "def_sacks": 0.0,
      "def_interceptions": 0,
      "fantasy_points_ppr": 6.3
    },
    {
      "season": 2008,
      "week": 12,
      "team": "SEA",
      "opponent": "WAS",
      "passing_yards": 0,
      "passing_tds": 0,
      "passing_interceptions": 0,
      "rushing_yards": 103,
      "rushing_tds": 0,
      "receptions": 3,
      "targets": 0,
      "receiving_yards": 10,
      "receiving_tds": 1,
      "def_tackles": 1,
      "def_sacks": 0.0,
      "def_interceptions": 0,
      "fantasy_points_ppr": 20.3
    },
    {
      "season": 2008,
      "week": 11,
      "team": "SEA",
      "opponent": "ARI",
      "passing_yards": 0,
      "passing_tds": 0,
      "passing_interceptions": 0,
      "rushing_yards": 2,
      "rushing_tds": 0,
      "receptions": 3,
      "targets": 0,
      "receiving_yards": 27,
      "receiving_tds": 1,
      "def_tackles": 1,
      "def_sacks": 0.0,
      "def_interceptions": 0,
      "fantasy_points_ppr": 11.9
    },
    {
      "season": 2008,
      "week": 10,
      "team": "SEA",
      "opponent": "MIA",
      "passing_yards": 0,
      "passing_tds": 0,
      "passing_interceptions": 0,
      "rushing_yards": 11,
      "rushing_tds": 0,
      "receptions": 1,
      "targets": 0,
      "receiving_yards": 6,
      "receiving_tds": 0,
      "def_tackles": 0,
      "def_sacks": 0.0,
      "def_interceptions": 0,
      "fantasy_points_ppr": 2.7
    },
    {
      "season": 2008,
      "week": 9,
      "team": "SEA",
      "opponent": "PHI",
      "passing_yards": 0,
      "passing_tds": 0,
      "passing_interceptions": 0,
      "rushing_yards": 43,
      "rushing_tds": 0,
      "receptions": 0,
      "targets": 0,
      "receiving_yards": 0,
      "receiving_tds": 0,
      "def_tackles": 0,
      "def_sacks": 0.0,
      "def_interceptions": 0,
      "fantasy_points_ppr": 4.3
    },
    {
      "season": 2008,
      "week": 8,
      "team": "SEA",
      "opponent": "SF",
      "passing_yards": 0,
      "passing_tds": 0,
      "passing_interceptions": 0,
      "rushing_yards": 16,
      "rushing_tds": 0,
      "receptions": 0,
      "targets": 0,
      "receiving_yards": 0,
      "receiving_tds": 0,
      "def_tackles": 0,
      "def_sacks": 0.0,
      "def_interceptions": 0,
      "fantasy_points_ppr": 1.6
    },
    {
      "season": 2008,
      "week": 7,
      "team": "SEA",
      "opponent": "TB",
      "passing_yards": 0,
      "passing_tds": 0,
      "passing_interceptions": 0,
      "rushing_yards": 56,
      "rushing_tds": 0,
      "receptions": 2,
      "targets": 0,
      "receiving_yards": 12,
      "receiving_tds": 0,
      "def_tackles": 0,
      "def_sacks": 0.0,
      "def_interceptions": 0,
      "fantasy_points_ppr": 8.8
    },
    {
      "season": 2008,
      "week": 6,
      "team": "SEA",
      "opponent": "GB",
      "passing_yards": 0,
      "passing_tds": 0,
      "passing_interceptions": 0,
      "rushing_yards": 16,
      "rushing_tds": 0,
      "receptions": 2,
      "targets": 0,
      "receiving_yards": 13,
      "receiving_tds": 0,
      "def_tackles": 1,
      "def_sacks": 0.0,
      "def_interceptions": 0,
      "fantasy_points_ppr": 4.9
    },
    {
      "season": 2008,
      "week": 1,
      "team": "SEA",
      "opponent": "BUF",
      "passing_yards": 0,
      "passing_tds": 0,
      "passing_interceptions": 0,
      "rushing_yards": 31,
      "rushing_tds": 0,
      "receptions": 0,
      "targets": 0,
      "receiving_yards": 0,
      "receiving_tds": 0,
      "def_tackles": 0,
      "def_sacks": 0.0,
      "def_interceptions": 0,
      "fantasy_points_ppr": 3.1
    },
    {
      "season": 2007,
      "week": 19,
      "team": "SEA",
      "opponent": "GB",
      "passing_yards": 0,
      "passing_tds": 0,
      "passing_interceptions": 0,
      "rushing_yards": -1,
      "rushing_tds": 0,
      "receptions": 0,
      "targets": 0,
      "receiving_yards": 0,
      "receiving_tds": 0,
      "def_tackles": 0,
      "def_sacks": 0.0,
      "def_interceptions": 0,
      "fantasy_points_ppr": -0.1
    },
    {
      "season": 2007,
      "week": 18,
      "team": "SEA",
      "opponent": "WAS",
      "passing_yards": 0,
      "passing_tds": 0,
      "passing_interceptions": 0,
      "rushing_yards": 13,
      "rushing_tds": 0,
      "receptions": 0,
      "targets": 0,
      "receiving_yards": 0,
      "receiving_tds": 0,
      "def_tackles": 0,
      "def_sacks": 0.0,
      "def_interceptions": 0,
      "fantasy_points_ppr": 1.3
    },
    {
      "season": 2007,
      "week": 17,
      "team": "SEA",
      "opponent": "ATL",
      "passing_yards": 0,
      "passing_tds": 0,
      "passing_interceptions": 0,
      "rushing_yards": 91,
      "rushing_tds": 1,
      "receptions": 4,
      "targets": 0,
      "receiving_yards": 18,
      "receiving_tds": 0,
      "def_tackles": 0,
      "def_sacks": 0.0,
      "def_interceptions": 0,
      "fantasy_points_ppr": 20.9
    },
    {
      "season": 2007,
      "week": 16,
      "team": "SEA",
      "opponent": "BAL",
      "passing_yards": 0,
      "passing_tds": 0,
      "passing_interceptions": 0,
      "rushing_yards": 40,
      "rushing_tds": 0,
      "receptions": 1,
      "targets": 0,
      "receiving_yards": -1,
      "receiving_tds": 0,
      "def_tackles": 0,
      "def_sacks": 0.0,
      "def_interceptions": 0,
      "fantasy_points_ppr": 4.9
    },
    {
      "season": 2007,
      "week": 15,
      "team": "SEA",
      "opponent": "CAR",
      "passing_yards": 0,
      "passing_tds": 0,
      "passing_interceptions": 0,
      "rushing_yards": 15,
      "rushing_tds": 0,
      "receptions": 4,
      "targets": 0,
      "receiving_yards": 31,
      "receiving_tds": 0,
      "def_tackles": 1,
      "def_sacks": 0.0,
      "def_interceptions": 0,
      "fantasy_points_ppr": 8.6
    },
    {
      "season": 2007,
      "week": 14,
      "team": "SEA",
      "opponent": "ARI",
      "passing_yards": 0,
      "passing_tds": 0,
      "passing_interceptions": 0,
      "rushing_yards": 36,
      "rushing_tds": 0,
      "receptions": 3,
      "targets": 0,
      "receiving_yards": 26,
      "receiving_tds": 0,
      "def_tackles": 0,
      "def_sacks": 0.0,
      "def_interceptions": 0,
      "fantasy_points_ppr": 9.2
    },
    {
      "season": 2007,
      "week": 13,
      "team": "SEA",
      "opponent": "PHI",
      "passing_yards": 0,
      "passing_tds": 0,
      "passing_interceptions": 0,
      "rushing_yards": 64,
      "rushing_tds": 1,
      "receptions": 0,
      "targets": 0,
      "receiving_yards": 0,
      "receiving_tds": 0,
      "def_tackles": 0,
      "def_sacks": 0.0,
      "def_interceptions": 0,
      "fantasy_points_ppr": 12.4
    },
    {
      "season": 2007,
      "week": 12,
      "team": "SEA",
      "opponent": "LA",
      "passing_yards": 0,
      "passing_tds": 0,
      "passing_interceptions": 0,
      "rushing_yards": 79,
      "rushing_tds": 0,
      "receptions": 1,
      "targets": 0,
      "receiving_yards": 5,
      "receiving_tds": 0,
      "def_tackles": 0,
      "def_sacks": 0.0,
      "def_interceptions": 0,
      "fantasy_points_ppr": 9.4
    },
    {
      "season": 2007,
      "week": 11,
      "team": "SEA",
      "opponent": "CHI",
      "passing_yards": 0,
      "passing_tds": 0,
      "passing_interceptions": 0,
      "rushing_yards": 87,
      "rushing_tds": 1,
      "receptions": 1,
      "targets": 0,
      "receiving_yards": 19,
      "receiving_tds": 0,
      "def_tackles": 0,
      "def_sacks": 0.0,
      "def_interceptions": 0,
      "fantasy_points_ppr": 17.6
    },
    {
      "season": 2007,
      "week": 10,
      "team": "SEA",
      "opponent": "SF",
      "passing_yards": 0,
      "passing_tds": 0,
      "passing_interceptions": 0,
      "rushing_yards": 87,
      "rushing_tds": 1,
      "receptions": 3,
      "targets": 0,
      "receiving_yards": 16,
      "receiving_tds": 0,
      "def_tackles": 1,
      "def_sacks": 0.0,
      "def_interceptions": 0,
      "fantasy_points_ppr": 17.3
    },
    {
      "season": 2007,
      "week": 9,
      "team": "SEA",
      "opponent": "CLE",
      "passing_yards": 0,
      "passing_tds": 0,
      "passing_interceptions": 0,
      "rushing_yards": 55,
      "rushing_tds": 0,
      "receptions": 2,
      "targets": 0,
      "receiving_yards": 43,
      "receiving_tds": 0,
      "def_tackles": 0,
      "def_sacks": 0.0,
      "def_interceptions": 0,
      "fantasy_points_ppr": 11.8
    },
    {
      "season": 2007,
      "week": 7,
      "team": "SEA",
      "opponent": "LA",
      "passing_yards": 0,
      "passing_tds": 0,
      "passing_interceptions": 0,
      "rushing_yards": 42,
      "rushing_tds": 0,
      "receptions": 2,
      "targets": 0,
      "receiving_yards": 18,
      "receiving_tds": 0,
      "def_tackles": 0,
      "def_sacks": 0.0,
      "def_interceptions": 0,
      "fantasy_points_ppr": 8.0
    },
    {
      "season": 2007,
      "week": 6,
      "team": "SEA",
      "opponent": "NO",
      "passing_yards": 0,
      "passing_tds": 0,
      "passing_interceptions": 0,
      "rushing_yards": 4,
      "rushing_tds": 0,
      "receptions": 0,
      "targets": 0,
      "receiving_yards": 0,
      "receiving_tds": 0,
      "def_tackles": 0,
      "def_sacks": 0.0,
      "def_interceptions": 0,
      "fantasy_points_ppr": 0.4
    },
    {
      "season": 2007,
      "week": 4,
      "team": "SEA",
      "opponent": "SF",
      "passing_yards": 0,
      "passing_tds": 0,
      "passing_interceptions": 0,
      "rushing_yards": 13,
      "rushing_tds": 0,
      "receptions": 1,
      "targets": 0,
      "receiving_yards": 4,
      "receiving_tds": 0,
      "def_tackles": 0,
      "def_sacks": 0.0,
      "def_interceptions": 0,
      "fantasy_points_ppr": 2.7
    },
    {
      "season": 2007,
      "week": 1,
      "team": "SEA",
      "opponent": "TB",
      "passing_yards": 0,
      "passing_tds": 0,
      "passing_interceptions": 0,
      "rushing_yards": 15,
      "rushing_tds": 0,
      "receptions": 1,
      "targets": 0,
      "receiving_yards": 34,
      "receiving_tds": 1,
      "def_tackles": 1,
      "def_sacks": 0.0,
      "def_interceptions": 0,
      "fantasy_points_ppr": 11.9
    },
    {
      "season": 2006,
      "week": 19,
      "team": "SEA",
      "opponent": "CHI",
      "passing_yards": 0,
      "passing_tds": 0,
      "passing_interceptions": 0,
      "rushing_yards": 11,
      "rushing_tds": 0,
      "receptions": 0,
      "targets": 0,
      "receiving_yards": 0,
      "receiving_tds": 0,
      "def_tackles": 0,
      "def_sacks": 0.0,
      "def_interceptions": 0,
      "fantasy_points_ppr": 1.1
    },
    {
      "season": 2006,
      "week": 18,
      "team": "SEA",
      "opponent": "DAL",
      "passing_yards": 0,
      "passing_tds": 0,
      "passing_interceptions": 0,
      "rushing_yards": 12,
      "rushing_tds": 0,
      "receptions": 0,
      "targets": 0,
      "receiving_yards": 0,
      "receiving_tds": 0,
      "def_tackles": 0,
      "def_sacks": 0.0,
      "def_interceptions": 0,
      "fantasy_points_ppr": 1.2
    },
    {
      "season": 2006,
      "week": 17,
      "team": "SEA",
      "opponent": "TB",
      "passing_yards": 0,
      "passing_tds": 0,
      "passing_interceptions": 0,
      "rushing_yards": 39,
      "rushing_tds": 0,
      "receptions": 1,
      "targets": 0,
      "receiving_yards": 8,
      "receiving_tds": 0,
      "def_tackles": 0,
      "def_sacks": 0.0,
      "def_interceptions": 0,
      "fantasy_points_ppr": 5.7
    },
    {
      "season": 2006,
      "week": 16,
      "team": "SEA",
      "opponent": "LAC",
      "passing_yards": 0,
      "passing_tds": 0,
      "passing_interceptions": 0,
      "rushing_yards": 3,
      "rushing_tds": 0,
      "receptions": 1,
      "targets": 0,
      "receiving_yards": 0,
      "receiving_tds": 0,
      "def_tackles": 0,
      "def_sacks": 0.0,
      "def_interceptions": 0,
      "fantasy_points_ppr": 1.3
    },
    {
      "season": 2006,
      "week": 15,
      "team": "SEA",
      "opponent": "SF",
      "passing_yards": 0,
      "passing_tds": 0,
      "passing_interceptions": 0,
      "rushing_yards": 14,
      "rushing_tds": 0,
      "receptions": 0,
      "targets": 0,
      "receiving_yards": 0,
      "receiving_tds": 0,
      "def_tackles": 0,
      "def_sacks": 0.0,
      "def_interceptions": 0,
      "fantasy_points_ppr": 1.4
    },
    {
      "season": 2006,
      "week": 14,
      "team": "SEA",
      "opponent": "ARI",
      "passing_yards": 0,
      "passing_tds": 0,
      "passing_interceptions": 0,
      "rushing_yards": 12,
      "rushing_tds": 0,
      "receptions": 1,
      "targets": 0,
      "receiving_yards": -5,
      "receiving_tds": 0,
      "def_tackles": 0,
      "def_sacks": 0.0,
      "def_interceptions": 0,
      "fantasy_points_ppr": 1.7
    },
    {
      "season": 2006,
      "week": 13,
      "team": "SEA",
      "opponent": "DEN",
      "passing_yards": 0,
      "passing_tds": 0,
      "passing_interceptions": 0,
      "rushing_yards": 7,
      "rushing_tds": 0,
      "receptions": 0,
      "targets": 0,
      "receiving_yards": 0,
      "receiving_tds": 0,
      "def_tackles": 0,
      "def_sacks": 0.0,
      "def_interceptions": 0,
      "fantasy_points_ppr": 0.7
    },
    {
      "season": 2006,
      "week": 12,
      "team": "SEA",
      "opponent": "GB",
      "passing_yards": 0,
      "passing_tds": 0,
      "passing_interceptions": 0,
      "rushing_yards": 6,
      "rushing_tds": 0,
      "receptions": 0,
      "targets": 0,
      "receiving_yards": 0,
      "receiving_tds": 0,
      "def_tackles": 0,
      "def_sacks": 0.0,
      "def_interceptions": 0,
      "fantasy_points_ppr": 0.6
    },
    {
      "season": 2006,
      "week": 11,
      "team": "SEA",
      "opponent": "SF",
      "passing_yards": 0,
      "passing_tds": 0,
      "passing_interceptions": 0,
      "rushing_yards": 12,
      "rushing_tds": 0,
      "receptions": 1,
      "targets": 0,
      "receiving_yards": -7,
      "receiving_tds": 0,
      "def_tackles": 0,
      "def_sacks": 0.0,
      "def_interceptions": 0,
      "fantasy_points_ppr": 1.5
    },
    {
      "season": 2006,
      "week": 10,
      "team": "SEA",
      "opponent": "LA",
      "passing_yards": 0,
      "passing_tds": 0,
      "passing_interceptions": 0,
      "rushing_yards": 124,
      "rushing_tds": 0,
      "receptions": 0,
      "targets": 0,
      "receiving_yards": 0,
      "receiving_tds": 0,
      "def_tackles": 0,
      "def_sacks": 0.0,
      "def_interceptions": 0,
      "fantasy_points_ppr": 12.4
    },
    {
      "season": 2006,
      "week": 9,
      "team": "SEA",
      "opponent": "LV",
      "passing_yards": 0,
      "passing_tds": 0,
      "passing_interceptions": 0,
      "rushing_yards": 138,
      "rushing_tds": 0,
      "receptions": 0,
      "targets": 0,
      "receiving_yards": 0,
      "receiving_tds": 0,
      "def_tackles": 0,
      "def_sacks": 0.0,
      "def_interceptions": 0,
      "fantasy_points_ppr": 13.8
    },
    {
      "season": 2006,
      "week": 8,
      "team": "SEA",
      "opponent": "KC",
      "passing_yards": 0,
      "passing_tds": 0,
      "passing_interceptions": 0,
      "rushing_yards": 25,
      "rushing_tds": 0,
      "receptions": 0,
      "targets": 0,
      "receiving_yards": 0,
      "receiving_tds": 0,
      "def_tackles": 0,
      "def_sacks": 0.0,
      "def_interceptions": 0,
      "fantasy_points_ppr": 2.5
    },
    {
      "season": 2006,
      "week": 7,
      "team": "SEA",
      "opponent": "MIN",
      "passing_yards": 0,
      "passing_tds": 0,
      "passing_interceptions": 0,
      "rushing_yards": 49,
      "rushing_tds": 0,
      "receptions": 2,
      "targets": 0,
      "receiving_yards": 9,
      "receiving_tds": 0,
      "def_tackles": 0,
      "def_sacks": 0.0,
      "def_interceptions": 0,
      "fantasy_points_ppr": 7.8
    },
    {
      "season": 2006,
      "week": 6,
      "team": "SEA",
      "opponent": "LA",
      "passing_yards": 0,
      "passing_tds": 0,
      "passing_interceptions": 0,
      "rushing_yards": 74,
      "rushing_tds": 0,
      "receptions": 2,
      "targets": 0,
      "receiving_yards": 6,
      "receiving_tds": 0,
      "def_tackles": 1,
      "def_sacks": 0.0,
      "def_interceptions": 0,
      "fantasy_points_ppr": 8.0
    },
    {
      "season": 2006,
      "week": 4,
      "team": "SEA",
      "opponent": "CHI",
      "passing_yards": 0,
      "passing_tds": 0,
      "passing_interceptions": 0,
      "rushing_yards": 35,
      "rushing_tds": 0,
      "receptions": 1,
      "targets": 0,
      "receiving_yards": 2,
      "receiving_tds": 0,
      "def_tackles": 0,
      "def_sacks": 0.0,
      "def_interceptions": 0,
      "fantasy_points_ppr": 4.7
    },
    {
      "season": 2006,
      "week": 3,
      "team": "SEA",
      "opponent": "NYG",
      "passing_yards": 0,
      "passing_tds": 0,
      "passing_interceptions": 0,
      "rushing_yards": 18,
      "rushing_tds": 0,
      "receptions": 0,
      "targets": 0,
      "receiving_yards": 0,
      "receiving_tds": 0,
      "def_tackles": 0,
      "def_sacks": 0.0,
      "def_interceptions": 0,
      "fantasy_points_ppr": 1.8
    },
    {
      "season": 2006,
      "week": 2,
      "team": "SEA",
      "opponent": "ARI",
      "passing_yards": 0,
      "passing_tds": 0,
      "passing_interceptions": 0,
      "rushing_yards": 25,
      "rushing_tds": 0,
      "receptions": 1,
      "targets": 0,
      "receiving_yards": 27,
      "receiving_tds": 0,
      "def_tackles": 0,
      "def_sacks": 0.0,
      "def_interceptions": 0,
      "fantasy_points_ppr": 6.2
    },
    {
      "season": 2006,
      "week": 1,
      "team": "SEA",
      "opponent": "DET",
      "passing_yards": 0,
      "passing_tds": 0,
      "passing_interceptions": 0,
      "rushing_yards": 23,
      "rushing_tds": 0,
      "receptions": 1,
      "targets": 0,
      "receiving_yards": 6,
      "receiving_tds": 0,
      "def_tackles": 0,
      "def_sacks": 0.0,
      "def_interceptions": 0,
      "fantasy_points_ppr": 3.9
    },
    {
      "season": 2005,
      "week": 21,
      "team": "SEA",
      "opponent": "PIT",
      "passing_yards": 0,
      "passing_tds": 0,
      "passing_interceptions": 0,
      "rushing_yards": 0,
      "rushing_tds": 0,
      "receptions": 1,
      "targets": 0,
      "receiving_yards": 6,
      "receiving_tds": 0,
      "def_tackles": 0,
      "def_sacks": 0.0,
      "def_interceptions": 0,
      "fantasy_points_ppr": 1.6
    },
    {
      "season": 2005,
      "week": 20,
      "team": "SEA",
      "opponent": "CAR",
      "passing_yards": 0,
      "passing_tds": 0,
      "passing_interceptions": 0,
      "rushing_yards": 24,
      "rushing_tds": 0,
      "receptions": 0,
      "targets": 0,
      "receiving_yards": 0,
      "receiving_tds": 0,
      "def_tackles": 1,
      "def_sacks": 0.0,
      "def_interceptions": 0,
      "fantasy_points_ppr": 2.4
    },
    {
      "season": 2005,
      "week": 19,
      "team": "SEA",
      "opponent": "WAS",
      "passing_yards": 0,
      "passing_tds": 0,
      "passing_interceptions": 0,
      "rushing_yards": 49,
      "rushing_tds": 0,
      "receptions": 1,
      "targets": 0,
      "receiving_yards": 16,
      "receiving_tds": 0,
      "def_tackles": 0,
      "def_sacks": 0.0,
      "def_interceptions": 0,
      "fantasy_points_ppr": 7.5
    },
    {
      "season": 2005,
      "week": 17,
      "team": "SEA",
      "opponent": "GB",
      "passing_yards": 0,
      "passing_tds": 0,
      "passing_interceptions": 0,
      "rushing_yards": 25,
      "rushing_tds": 0,
      "receptions": 2,
      "targets": 0,
      "receiving_yards": 19,
      "receiving_tds": 0,
      "def_tackles": 0,
      "def_sacks": 0.0,
      "def_interceptions": 0,
      "fantasy_points_ppr": 6.4
    },
    {
      "season": 2005,
      "week": 16,
      "team": "SEA",
      "opponent": "IND",
      "passing_yards": 0,
      "passing_tds": 0,
      "passing_interceptions": 0,
      "rushing_yards": 34,
      "rushing_tds": 0,
      "receptions": 1,
      "targets": 0,
      "receiving_yards": 3,
      "receiving_tds": 0,
      "def_tackles": 0,
      "def_sacks": 0.0,
      "def_interceptions": 0,
      "fantasy_points_ppr": 4.7
    },
    {
      "season": 2005,
      "week": 15,
      "team": "SEA",
      "opponent": "TEN",
      "passing_yards": 0,
      "passing_tds": 0,
      "passing_interceptions": 0,
      "rushing_yards": 3,
      "rushing_tds": 0,
      "receptions": 1,
      "targets": 0,
      "receiving_yards": 14,
      "receiving_tds": 0,
      "def_tackles": 0,
      "def_sacks": 0.0,
      "def_interceptions": 0,
      "fantasy_points_ppr": 2.7
    },
    {
      "season": 2005,
      "week": 14,
      "team": "SEA",
      "opponent": "SF",
      "passing_yards": 0,
      "passing_tds": 0,
      "passing_interceptions": 0,
      "rushing_yards": 22,
      "rushing_tds": 0,
      "receptions": 0,
      "targets": 0,
      "receiving_yards": 0,
      "receiving_tds": 0,
      "def_tackles": 1,
      "def_sacks": 0.0,
      "def_interceptions": 0,
      "fantasy_points_ppr": 2.2
    },
    {
      "season": 2005,
      "week": 13,
      "team": "SEA",
      "opponent": "PHI",
      "passing_yards": 0,
      "passing_tds": 0,
      "passing_interceptions": 0,
      "rushing_yards": 33,
      "rushing_tds": 0,
      "receptions": 0,
      "targets": 0,
      "receiving_yards": 0,
      "receiving_tds": 0,
      "def_tackles": 1,
      "def_sacks": 0.0,
      "def_interceptions": 0,
      "fantasy_points_ppr": 3.3
    },
    {
      "season": 2005,
      "week": 11,
      "team": "SEA",
      "opponent": "SF",
      "passing_yards": 0,
      "passing_tds": 0,
      "passing_interceptions": 0,
      "rushing_yards": 17,
      "rushing_tds": 0,
      "receptions": 0,
      "targets": 0,
      "receiving_yards": 0,
      "receiving_tds": 0,
      "def_tackles": 1,
      "def_sacks": 0.0,
      "def_interceptions": 0,
      "fantasy_points_ppr": 1.7
    },
    {
      "season": 2005,
      "week": 10,
      "team": "SEA",
      "opponent": "LA",
      "passing_yards": 0,
      "passing_tds": 0,
      "passing_interceptions": 0,
      "rushing_yards": 0,
      "rushing_tds": 0,
      "receptions": 0,
      "targets": 0,
      "receiving_yards": 0,
      "receiving_tds": 0,
      "def_tackles": 2,
      "def_sacks": 0.0,
      "def_interceptions": 0,
      "fantasy_points_ppr": 0.0
    },
    {
      "season": 2005,
      "week": 9,
      "team": "SEA",
      "opponent": "ARI",
      "passing_yards": 0,
      "passing_tds": 0,
      "passing_interceptions": 0,
      "rushing_yards": 30,
      "rushing_tds": 0,
      "receptions": 1,
      "targets": 0,
      "receiving_yards": 12,
      "receiving_tds": 0,
      "def_tackles": 0,
      "def_sacks": 0.0,
      "def_interceptions": 0,
      "fantasy_points_ppr": 5.2
    },
    {
      "season": 2005,
      "week": 6,
      "team": "SEA",
      "opponent": "HOU",
      "passing_yards": 0,
      "passing_tds": 0,
      "passing_interceptions": 0,
      "rushing_yards": 104,
      "rushing_tds": 1,
      "receptions": 0,
      "targets": 0,
      "receiving_yards": 0,
      "receiving_tds": 0,
      "def_tackles": 0,
      "def_sacks": 0.0,
      "def_interceptions": 0,
      "fantasy_points_ppr": 16.4
    },
    {
      "season": 2005,
      "week": 5,
      "team": "SEA",
      "opponent": "LA",
      "passing_yards": 0,
      "passing_tds": 0,
      "passing_interceptions": 0,
      "rushing_yards": 0,
      "rushing_tds": 0,
      "receptions": 0,
      "targets": 0,
      "receiving_yards": 0,
      "receiving_tds": 0,
      "def_tackles": 2,
      "def_sacks": 0.0,
      "def_interceptions": 0,
      "fantasy_points_ppr": 0.0
    },
    {
      "season": 2005,
      "week": 4,
      "team": "SEA",
      "opponent": "WAS",
      "passing_yards": 0,
      "passing_tds": 0,
      "passing_interceptions": 0,
      "rushing_yards": 0,
      "rushing_tds": 0,
      "receptions": 0,
      "targets": 0,
      "receiving_yards": 0,
      "receiving_tds": 0,
      "def_tackles": 0,
      "def_sacks": 0.0,
      "def_interceptions": 0,
      "fantasy_points_ppr": 0.0
    },
    {
      "season": 2005,
      "week": 3,
      "team": "SEA",
      "opponent": "ARI",
      "passing_yards": 0,
      "passing_tds": 0,
      "passing_interceptions": 0,
      "rushing_yards": 4,
      "rushing_tds": 0,
      "receptions": 0,
      "targets": 0,
      "receiving_yards": 0,
      "receiving_tds": 0,
      "def_tackles": 0,
      "def_sacks": 0.0,
      "def_interceptions": 0,
      "fantasy_points_ppr": 0.4
    },
    {
      "season": 2005,
      "week": 2,
      "team": "SEA",
      "opponent": "ATL",
      "passing_yards": 0,
      "passing_tds": 0,
      "passing_interceptions": 0,
      "rushing_yards": 10,
      "rushing_tds": 0,
      "receptions": 0,
      "targets": 0,
      "receiving_yards": 0,
      "receiving_tds": 0,
      "def_tackles": 0,
      "def_sacks": 0.0,
      "def_interceptions": 0,
      "fantasy_points_ppr": 1.0
    },
    {
      "season": 2005,
      "week": 1,
      "team": "SEA",
      "opponent": "JAX",
      "passing_yards": 0,
      "passing_tds": 0,
      "passing_interceptions": 0,
      "rushing_yards": 6,
      "rushing_tds": 0,
      "receptions": 0,
      "targets": 0,
      "receiving_yards": 0,
      "receiving_tds": 0,
      "def_tackles": 0,
      "def_sacks": 0.0,
      "def_interceptions": 0,
      "fantasy_points_ppr": 0.6
    },
    {
      "season": 2004,
      "week": 18,
      "team": "SEA",
      "opponent": "LA",
      "passing_yards": 0,
      "passing_tds": 0,
      "passing_interceptions": 0,
      "rushing_yards": 9,
      "rushing_tds": 0,
      "receptions": 0,
      "targets": 0,
      "receiving_yards": 0,
      "receiving_tds": 0,
      "def_tackles": 0,
      "def_sacks": 0.0,
      "def_interceptions": 0,
      "fantasy_points_ppr": 0.9
    },
    {
      "season": 2004,
      "week": 17,
      "team": "SEA",
      "opponent": "ATL",
      "passing_yards": 0,
      "passing_tds": 0,
      "passing_interceptions": 0,
      "rushing_yards": 0,
      "rushing_tds": 0,
      "receptions": 1,
      "targets": 0,
      "receiving_yards": 6,
      "receiving_tds": 0,
      "def_tackles": 0,
      "def_sacks": 0.0,
      "def_interceptions": 0,
      "fantasy_points_ppr": 1.6
    },
    {
      "season": 2004,
      "week": 16,
      "team": "SEA",
      "opponent": "ARI",
      "passing_yards": 0,
      "passing_tds": 0,
      "passing_interceptions": 0,
      "rushing_yards": 10,
      "rushing_tds": 0,
      "receptions": 1,
      "targets": 0,
      "receiving_yards": 3,
      "receiving_tds": 0,
      "def_tackles": 0,
      "def_sacks": 0.0,
      "def_interceptions": 0,
      "fantasy_points_ppr": 2.3
    },
    {
      "season": 2004,
      "week": 15,
      "team": "SEA",
      "opponent": "NYJ",
      "passing_yards": 0,
      "passing_tds": 0,
      "passing_interceptions": 0,
      "rushing_yards": 6,
      "rushing_tds": 0,
      "receptions": 0,
      "targets": 0,
      "receiving_yards": 0,
      "receiving_tds": 0,
      "def_tackles": 0,
      "def_sacks": 0.0,
      "def_interceptions": 0,
      "fantasy_points_ppr": 0.6
    },
    {
      "season": 2004,
      "week": 14,
      "team": "SEA",
      "opponent": "MIN",
      "passing_yards": 0,
      "passing_tds": 0,
      "passing_interceptions": 0,
      "rushing_yards": 13,
      "rushing_tds": 0,
      "receptions": 1,
      "targets": 0,
      "receiving_yards": 12,
      "receiving_tds": 0,
      "def_tackles": 0,
      "def_sacks": 0.0,
      "def_interceptions": 0,
      "fantasy_points_ppr": 3.5
    },
    {
      "season": 2004,
      "week": 13,
      "team": "SEA",
      "opponent": "DAL",
      "passing_yards": 0,
      "passing_tds": 0,
      "passing_interceptions": 0,
      "rushing_yards": 6,
      "rushing_tds": 0,
      "receptions": 0,
      "targets": 0,
      "receiving_yards": 0,
      "receiving_tds": 0,
      "def_tackles": 0,
      "def_sacks": 0.0,
      "def_interceptions": 0,
      "fantasy_points_ppr": 0.6
    },
    {
      "season": 2004,
      "week": 12,
      "team": "SEA",
      "opponent": "BUF",
      "passing_yards": 0,
      "passing_tds": 0,
      "passing_interceptions": 0,
      "rushing_yards": 10,
      "rushing_tds": 0,
      "receptions": 2,
      "targets": 0,
      "receiving_yards": 10,
      "receiving_tds": 0,
      "def_tackles": 0,
      "def_sacks": 0.0,
      "def_interceptions": 0,
      "fantasy_points_ppr": 4.0
    },
    {
      "season": 2004,
      "week": 11,
      "team": "SEA",
      "opponent": "MIA",
      "passing_yards": 0,
      "passing_tds": 0,
      "passing_interceptions": 0,
      "rushing_yards": 3,
      "rushing_tds": 0,
      "receptions": 0,
      "targets": 0,
      "receiving_yards": 0,
      "receiving_tds": 0,
      "def_tackles": 1,
      "def_sacks": 0.0,
      "def_interceptions": 0,
      "fantasy_points_ppr": 0.3
    },
    {
      "season": 2004,
      "week": 10,
      "team": "SEA",
      "opponent": "LA",
      "passing_yards": 0,
      "passing_tds": 0,
      "passing_interceptions": 0,
      "rushing_yards": 3,
      "rushing_tds": 0,
      "receptions": 1,
      "targets": 0,
      "receiving_yards": 8,
      "receiving_tds": 0,
      "def_tackles": 1,
      "def_sacks": 0.0,
      "def_interceptions": 0,
      "fantasy_points_ppr": 2.1
    },
    {
      "season": 2004,
      "week": 8,
      "team": "SEA",
      "opponent": "CAR",
      "passing_yards": 0,
      "passing_tds": 0,
      "passing_interceptions": 0,
      "rushing_yards": 0,
      "rushing_tds": 0,
      "receptions": 0,
      "targets": 0,
      "receiving_yards": 0,
      "receiving_tds": 0,
      "def_tackles": 0,
      "def_sacks": 0.0,
      "def_interceptions": 0,
      "fantasy_points_ppr": 0.0
    },
    {
      "season": 2004,
      "week": 7,
      "team": "SEA",
      "opponent": "ARI",
      "passing_yards": 0,
      "passing_tds": 0,
      "passing_interceptions": 0,
      "rushing_yards": 0,
      "rushing_tds": 0,
      "receptions": 0,
      "targets": 0,
      "receiving_yards": 0,
      "receiving_tds": 0,
      "def_tackles": 0,
      "def_sacks": 0.0,
      "def_interceptions": 0,
      "fantasy_points_ppr": 0.0
    },
    {
      "season": 2004,
      "week": 6,
      "team": "SEA",
      "opponent": "NE",
      "passing_yards": 0,
      "passing_tds": 0,
      "passing_interceptions": 0,
      "rushing_yards": 16,
      "rushing_tds": 0,
      "receptions": 1,
      "targets": 0,
      "receiving_yards": 7,
      "receiving_tds": 0,
      "def_tackles": 0,
      "def_sacks": 0.0,
      "def_interceptions": 0,
      "fantasy_points_ppr": 3.3
    },
    {
      "season": 2004,
      "week": 5,
      "team": "SEA",
      "opponent": "LA",
      "passing_yards": 0,
      "passing_tds": 0,
      "passing_interceptions": 0,
      "rushing_yards": 5,
      "rushing_tds": 0,
      "receptions": 0,
      "targets": 0,
      "receiving_yards": 0,
      "receiving_tds": 0,
      "def_tackles": 1,
      "def_sacks": 0.0,
      "def_interceptions": 0,
      "fantasy_points_ppr": 0.5
    },
    {
      "season": 2004,
      "week": 3,
      "team": "SEA",
      "opponent": "SF",
      "passing_yards": 0,
      "passing_tds": 0,
      "passing_interceptions": 0,
      "rushing_yards": 42,
      "rushing_tds": 0,
      "receptions": 1,
      "targets": 0,
      "receiving_yards": 5,
      "receiving_tds": 0,
      "def_tackles": 2,
      "def_sacks": 0.0,
      "def_interceptions": 0,
      "fantasy_points_ppr": 5.7
    },
    {
      "season": 2004,
      "week": 2,
      "team": "SEA",
      "opponent": "TB",
      "passing_yards": 0,
      "passing_tds": 0,
      "passing_interceptions": 0,
      "rushing_yards": 2,
      "rushing_tds": 0,
      "receptions": 1,
      "targets": 0,
      "receiving_yards": 2,
      "receiving_tds": 0,
      "def_tackles": 0,
      "def_sacks": 0.0,
      "def_interceptions": 0,
      "fantasy_points_ppr": 1.4
    },
    {
      "season": 2004,
      "week": 1,
      "team": "SEA",
      "opponent": "NO",
      "passing_yards": 0,
      "passing_tds": 0,
      "passing_interceptions": 0,
      "rushing_yards": 10,
      "rushing_tds": 0,
      "receptions": 0,
      "targets": 0,
      "receiving_yards": 0,
      "receiving_tds": 0,
      "def_tackles": 0,
      "def_sacks": 0.0,
      "def_interceptions": 0,
      "fantasy_points_ppr": 1.0
    },
    {
      "season": 2003,
      "week": 18,
      "team": "SEA",
      "opponent": "GB",
      "passing_yards": 0,
      "passing_tds": 0,
      "passing_interceptions": 0,
      "rushing_yards": 4,
      "rushing_tds": 0,
      "receptions": 0,
      "targets": 0,
      "receiving_yards": 0,
      "receiving_tds": 0,
      "def_tackles": 0,
      "def_sacks": 0.0,
      "def_interceptions": 0,
      "fantasy_points_ppr": 0.4
    },
    {
      "season": 2003,
      "week": 17,
      "team": "SEA",
      "opponent": "SF",
      "passing_yards": 0,
      "passing_tds": 0,
      "passing_interceptions": 0,
      "rushing_yards": 11,
      "rushing_tds": 0,
      "receptions": 0,
      "targets": 0,
      "receiving_yards": 0,
      "receiving_tds": 0,
      "def_tackles": 0,
      "def_sacks": 0.0,
      "def_interceptions": 0,
      "fantasy_points_ppr": 1.1
    },
    {
      "season": 2003,
      "week": 16,
      "team": "SEA",
      "opponent": "ARI",
      "passing_yards": 0,
      "passing_tds": 0,
      "passing_interceptions": 0,
      "rushing_yards": 13,
      "rushing_tds": 0,
      "receptions": 1,
      "targets": 0,
      "receiving_yards": 4,
      "receiving_tds": 1,
      "def_tackles": 0,
      "def_sacks": 0.0,
      "def_interceptions": 0,
      "fantasy_points_ppr": 8.7
    },
    {
      "season": 2003,
      "week": 15,
      "team": "SEA",
      "opponent": "LA",
      "passing_yards": 0,
      "passing_tds": 0,
      "passing_interceptions": 0,
      "rushing_yards": 9,
      "rushing_tds": 0,
      "receptions": 0,
      "targets": 0,
      "receiving_yards": 0,
      "receiving_tds": 0,
      "def_tackles": 0,
      "def_sacks": 0.0,
      "def_interceptions": 0,
      "fantasy_points_ppr": 0.9
    },
    {
      "season": 2003,
      "week": 14,
      "team": "SEA",
      "opponent": "MIN",
      "passing_yards": 0,
      "passing_tds": 0,
      "passing_interceptions": 0,
      "rushing_yards": 0,
      "rushing_tds": 0,
      "receptions": 0,
      "targets": 0,
      "receiving_yards": 0,
      "receiving_tds": 0,
      "def_tackles": 0,
      "def_sacks": 0.0,
      "def_interceptions": 0,
      "fantasy_points_ppr": 0.0
    },
    {
      "season": 2003,
      "week": 13,
      "team": "SEA",
      "opponent": "CLE",
      "passing_yards": 0,
      "passing_tds": 0,
      "passing_interceptions": 0,
      "rushing_yards": 0,
      "rushing_tds": 0,
      "receptions": 0,
      "targets": 0,
      "receiving_yards": 0,
      "receiving_tds": 0,
      "def_tackles": 0,
      "def_sacks": 0.0,
      "def_interceptions": 0,
      "fantasy_points_ppr": 0.0
    },
    {
      "season": 2003,
      "week": 12,
      "team": "SEA",
      "opponent": "BAL",
      "passing_yards": 0,
      "passing_tds": 0,
      "passing_interceptions": 0,
      "rushing_yards": 2,
      "rushing_tds": 0,
      "receptions": 0,
      "targets": 0,
      "receiving_yards": 0,
      "receiving_tds": 0,
      "def_tackles": 0,
      "def_sacks": 0.0,
      "def_interceptions": 0,
      "fantasy_points_ppr": 0.2
    },
    {
      "season": 2003,
      "week": 11,
      "team": "SEA",
      "opponent": "DET",
      "passing_yards": 0,
      "passing_tds": 0,
      "passing_interceptions": 0,
      "rushing_yards": 17,
      "rushing_tds": 0,
      "receptions": 0,
      "targets": 0,
      "receiving_yards": 0,
      "receiving_tds": 0,
      "def_tackles": 0,
      "def_sacks": 0.0,
      "def_interceptions": 0,
      "fantasy_points_ppr": 1.7
    },
    {
      "season": 2003,
      "week": 10,
      "team": "SEA",
      "opponent": "WAS",
      "passing_yards": 0,
      "passing_tds": 0,
      "passing_interceptions": 0,
      "rushing_yards": 26,
      "rushing_tds": 0,
      "receptions": 0,
      "targets": 0,
      "receiving_yards": 0,
      "receiving_tds": 0,
      "def_tackles": 2,
      "def_sacks": 0.0,
      "def_interceptions": 0,
      "fantasy_points_ppr": 2.6
    },
    {
      "season": 2003,
      "week": 9,
      "team": "SEA",
      "opponent": "PIT",
      "passing_yards": 0,
      "passing_tds": 0,
      "passing_interceptions": 0,
      "rushing_yards": 47,
      "rushing_tds": 0,
      "receptions": 0,
      "targets": 0,
      "receiving_yards": 0,
      "receiving_tds": 0,
      "def_tackles": 0,
      "def_sacks": 0.0,
      "def_interceptions": 0,
      "fantasy_points_ppr": 4.7
    },
    {
      "season": 2003,
      "week": 8,
      "team": "SEA",
      "opponent": "CIN",
      "passing_yards": 0,
      "passing_tds": 0,
      "passing_interceptions": 0,
      "rushing_yards": 24,
      "rushing_tds": 0,
      "receptions": 0,
      "targets": 0,
      "receiving_yards": 0,
      "receiving_tds": 0,
      "def_tackles": 0,
      "def_sacks": 0.0,
      "def_interceptions": 0,
      "fantasy_points_ppr": 2.4
    },
    {
      "season": 2003,
      "week": 7,
      "team": "SEA",
      "opponent": "CHI",
      "passing_yards": 0,
      "passing_tds": 0,
      "passing_interceptions": 0,
      "rushing_yards": 0,
      "rushing_tds": 0,
      "receptions": 0,
      "targets": 0,
      "receiving_yards": 0,
      "receiving_tds": 0,
      "def_tackles": 0,
      "def_sacks": 0.0,
      "def_interceptions": 0,
      "fantasy_points_ppr": 0.0
    },
    {
      "season": 2003,
      "week": 6,
      "team": "SEA",
      "opponent": "SF",
      "passing_yards": 0,
      "passing_tds": 0,
      "passing_interceptions": 0,
      "rushing_yards": 5,
      "rushing_tds": 0,
      "receptions": 0,
      "targets": 0,
      "receiving_yards": 0,
      "receiving_tds": 0,
      "def_tackles": 0,
      "def_sacks": 0.0,
      "def_interceptions": 0,
      "fantasy_points_ppr": 0.5
    },
    {
      "season": 2003,
      "week": 5,
      "team": "SEA",
      "opponent": "GB",
      "passing_yards": 0,
      "passing_tds": 0,
      "passing_interceptions": 0,
      "rushing_yards": 18,
      "rushing_tds": 0,
      "receptions": 0,
      "targets": 0,
      "receiving_yards": 0,
      "receiving_tds": 0,
      "def_tackles": 1,
      "def_sacks": 0.0,
      "def_interceptions": 0,
      "fantasy_points_ppr": 1.8
    },
    {
      "season": 2003,
      "week": 3,
      "team": "SEA",
      "opponent": "LA",
      "passing_yards": 0,
      "passing_tds": 0,
      "passing_interceptions": 0,
      "rushing_yards": 0,
      "rushing_tds": 0,
      "receptions": 3,
      "targets": 0,
      "receiving_yards": 28,
      "receiving_tds": 0,
      "def_tackles": 0,
      "def_sacks": 0.0,
      "def_interceptions": 0,
      "fantasy_points_ppr": 5.8
    },
    {
      "season": 2003,
      "week": 2,
      "team": "SEA",
      "opponent": "ARI",
      "passing_yards": 0,
      "passing_tds": 0,
      "passing_interceptions": 0,
      "rushing_yards": 67,
      "rushing_tds": 0,
      "receptions": 0,
      "targets": 0,
      "receiving_yards": 0,
      "receiving_tds": 0,
      "def_tackles": 0,
      "def_sacks": 0.0,
      "def_interceptions": 0,
      "fantasy_points_ppr": 6.7
    },
    {
      "season": 2003,
      "week": 1,
      "team": "SEA",
      "opponent": "NO",
      "passing_yards": 0,
      "passing_tds": 0,
      "passing_interceptions": 0,
      "rushing_yards": 0,
      "rushing_tds": 0,
      "receptions": 0,
      "targets": 0,
      "receiving_yards": 0,
      "receiving_tds": 0,
      "def_tackles": 0,
      "def_sacks": 0.0,
      "def_interceptions": 0,
      "fantasy_points_ppr": 0.0
    },
    {
      "season": 2002,
      "week": 14,
      "team": "SEA",
      "opponent": "PHI",
      "passing_yards": 0,
      "passing_tds": 0,
      "passing_interceptions": 0,
      "rushing_yards": 0,
      "rushing_tds": 0,
      "receptions": 0,
      "targets": 0,
      "receiving_yards": 0,
      "receiving_tds": 0,
      "def_tackles": 0,
      "def_sacks": 0.0,
      "def_interceptions": 0,
      "fantasy_points_ppr": 0.0
    },
    {
      "season": 2002,
      "week": 13,
      "team": "SEA",
      "opponent": "SF",
      "passing_yards": 0,
      "passing_tds": 0,
      "passing_interceptions": 0,
      "rushing_yards": -2,
      "rushing_tds": 0,
      "receptions": 0,
      "targets": 0,
      "receiving_yards": 0,
      "receiving_tds": 0,
      "def_tackles": 0,
      "def_sacks": 0.0,
      "def_interceptions": 0,
      "fantasy_points_ppr": -0.2
    },
    {
      "season": 2002,
      "week": 10,
      "team": "SEA",
      "opponent": "ARI",
      "passing_yards": 0,
      "passing_tds": 0,
      "passing_interceptions": 0,
      "rushing_yards": 72,
      "rushing_tds": 0,
      "receptions": 1,
      "targets": 1,
      "receiving_yards": 7,
      "receiving_tds": 0,
      "def_tackles": 1,
      "def_sacks": 0.0,
      "def_interceptions": 0,
      "fantasy_points_ppr": 8.9
    },
    {
      "season": 2002,
      "week": 9,
      "team": "SEA",
      "opponent": "WAS",
      "passing_yards": 0,
      "passing_tds": 0,
      "passing_interceptions": 0,
      "rushing_yards": 0,
      "rushing_tds": 0,
      "receptions": 0,
      "targets": 0,
      "receiving_yards": 0,
      "receiving_tds": 0,
      "def_tackles": 0,
      "def_sacks": 0.0,
      "def_interceptions": 0,
      "fantasy_points_ppr": 0.0
    },
    {
      "season": 2002,
      "week": 8,
      "team": "SEA",
      "opponent": "DAL",
      "passing_yards": 0,
      "passing_tds": 0,
      "passing_interceptions": 0,
      "rushing_yards": 24,
      "rushing_tds": 0,
      "receptions": 0,
      "targets": 0,
      "receiving_yards": 0,
      "receiving_tds": 0,
      "def_tackles": 0,
      "def_sacks": 0.0,
      "def_interceptions": 0,
      "fantasy_points_ppr": 2.4
    },
    {
      "season": 2002,
      "week": 7,
      "team": "SEA",
      "opponent": "LA",
      "passing_yards": 0,
      "passing_tds": 0,
      "passing_interceptions": 0,
      "rushing_yards": 21,
      "rushing_tds": 0,
      "receptions": 1,
      "targets": 1,
      "receiving_yards": 12,
      "receiving_tds": 0,
      "def_tackles": 0,
      "def_sacks": 0.0,
      "def_interceptions": 0,
      "fantasy_points_ppr": 10.3
    },
    {
      "season": 2002,
      "week": 6,
      "team": "SEA",
      "opponent": "SF",
      "passing_yards": 0,
      "passing_tds": 0,
      "passing_interceptions": 0,
      "rushing_yards": 0,
      "rushing_tds": 0,
      "receptions": 0,
      "targets": 0,
      "receiving_yards": 0,
      "receiving_tds": 0,
      "def_tackles": 0,
      "def_sacks": 0.0,
      "def_interceptions": 0,
      "fantasy_points_ppr": 0.0
    },
    {
      "season": 2002,
      "week": 4,
      "team": "SEA",
      "opponent": "MIN",
      "passing_yards": 0,
      "passing_tds": 0,
      "passing_interceptions": 0,
      "rushing_yards": 3,
      "rushing_tds": 0,
      "receptions": 0,
      "targets": 0,
      "receiving_yards": 0,
      "receiving_tds": 0,
      "def_tackles": 1,
      "def_sacks": 0.0,
      "def_interceptions": 0,
      "fantasy_points_ppr": 0.3
    },
    {
      "season": 2002,
      "week": 3,
      "team": "SEA",
      "opponent": "NYG",
      "passing_yards": 0,
      "passing_tds": 0,
      "passing_interceptions": 0,
      "rushing_yards": 0,
      "rushing_tds": 0,
      "receptions": 0,
      "targets": 0,
      "receiving_yards": 0,
      "receiving_tds": 0,
      "def_tackles": 1,
      "def_sacks": 0.0,
      "def_interceptions": 0,
      "fantasy_points_ppr": 0.0
    },
    {
      "season": 2002,
      "week": 2,
      "team": "SEA",
      "opponent": "ARI",
      "passing_yards": 0,
      "passing_tds": 0,
      "passing_interceptions": 0,
      "rushing_yards": 35,
      "rushing_tds": 0,
      "receptions": 1,
      "targets": 1,
      "receiving_yards": 6,
      "receiving_tds": 0,
      "def_tackles": 0,
      "def_sacks": 0.0,
      "def_interceptions": 0,
      "fantasy_points_ppr": 3.1
    },
    {
      "season": 2002,
      "week": 1,
      "team": "SEA",
      "opponent": "LV",
      "passing_yards": 0,
      "passing_tds": 0,
      "passing_interceptions": 0,
      "rushing_yards": 0,
      "rushing_tds": 0,
      "receptions": 0,
      "targets": 0,
      "receiving_yards": 0,
      "receiving_tds": 0,
      "def_tackles": 0,
      "def_sacks": 0.0,
      "def_interceptions": 0,
      "fantasy_points_ppr": 0.0
    }
  ],
  "injuries_recent": [
    {
      "season": 2025.0,
      "week": 16.0,
      "team": "SEA",
      "report_status": "",
      "practice_status": "Full Participation in Practice",
      "injury": ""
    },
    {
      "season": 2025.0,
      "week": 13.0,
      "team": "SEA",
      "report_status": "",
      "practice_status": "Full Participation in Practice",
      "injury": ""
    },
    {
      "season": 2025.0,
      "week": 12.0,
      "team": "SEA",
      "report_status": "",
      "practice_status": "Full Participation in Practice",
      "injury": ""
    },
    {
      "season": 2024.0,
      "week": 8.0,
      "team": "SEA",
      "report_status": "Questionable",
      "practice_status": "Full Participation in Practice",
      "injury": "Ankle"
    },
    {
      "season": 2023.0,
      "week": 2.0,
      "team": "SEA",
      "report_status": "Out",
      "practice_status": "Did Not Participate In Practice",
      "injury": "Shoulder"
    },
    {
      "season": 2023.0,
      "week": 1.0,
      "team": "SEA",
      "report_status": "",
      "practice_status": "Full Participation in Practice",
      "injury": ""
    }
  ],
  "snap_counts_recent": [
    {
      "season": 2025,
      "week": 22,
      "team": "SEA",
      "offense_snaps": 0.0,
      "defense_snaps": 3.0,
      "special_teams_snaps": 25.0
    },
    {
      "season": 2025,
      "week": 21,
      "team": "SEA",
      "offense_snaps": 0.0,
      "defense_snaps": 0.0,
      "special_teams_snaps": 21.0
    },
    {
      "season": 2025,
      "week": 20,
      "team": "SEA",
      "offense_snaps": 0.0,
      "defense_snaps": 9.0,
      "special_teams_snaps": 20.0
    },
    {
      "season": 2025,
      "week": 18,
      "team": "SEA",
      "offense_snaps": 0.0,
      "defense_snaps": 0.0,
      "special_teams_snaps": 15.0
    },
    {
      "season": 2025,
      "week": 17,
      "team": "SEA",
      "offense_snaps": 0.0,
      "defense_snaps": 9.0,
      "special_teams_snaps": 19.0
    },
    {
      "season": 2025,
      "week": 16,
      "team": "SEA",
      "offense_snaps": 0.0,
      "defense_snaps": 5.0,
      "special_teams_snaps": 20.0
    },
    {
      "season": 2025,
      "week": 15,
      "team": "SEA",
      "offense_snaps": 0.0,
      "defense_snaps": 2.0,
      "special_teams_snaps": 26.0
    },
    {
      "season": 2025,
      "week": 14,
      "team": "SEA",
      "offense_snaps": 0.0,
      "defense_snaps": 7.0,
      "special_teams_snaps": 25.0
    },
    {
      "season": 2025,
      "week": 13,
      "team": "SEA",
      "offense_snaps": 0.0,
      "defense_snaps": 12.0,
      "special_teams_snaps": 23.0
    },
    {
      "season": 2025,
      "week": 12,
      "team": "SEA",
      "offense_snaps": 0.0,
      "defense_snaps": 11.0,
      "special_teams_snaps": 21.0
    },
    {
      "season": 2025,
      "week": 11,
      "team": "SEA",
      "offense_snaps": 0.0,
      "defense_snaps": 0.0,
      "special_teams_snaps": 24.0
    },
    {
      "season": 2025,
      "week": 10,
      "team": "SEA",
      "offense_snaps": 0.0,
      "defense_snaps": 19.0,
      "special_teams_snaps": 26.0
    },
    {
      "season": 2025,
      "week": 9,
      "team": "SEA",
      "offense_snaps": 0.0,
      "defense_snaps": 18.0,
      "special_teams_snaps": 22.0
    },
    {
      "season": 2025,
      "week": 7,
      "team": "SEA",
      "offense_snaps": 0.0,
      "defense_snaps": 8.0,
      "special_teams_snaps": 18.0
    },
    {
      "season": 2025,
      "week": 6,
      "team": "SEA",
      "offense_snaps": 0.0,
      "defense_snaps": 14.0,
      "special_teams_snaps": 21.0
    },
    {
      "season": 2025,
      "week": 5,
      "team": "SEA",
      "offense_snaps": 0.0,
      "defense_snaps": 24.0,
      "special_teams_snaps": 21.0
    },
    {
      "season": 2025,
      "week": 4,
      "team": "SEA",
      "offense_snaps": 0.0,
      "defense_snaps": 9.0,
      "special_teams_snaps": 20.0
    },
    {
      "season": 2025,
      "week": 3,
      "team": "SEA",
      "offense_snaps": 0.0,
      "defense_snaps": 18.0,
      "special_teams_snaps": 20.0
    },
    {
      "season": 2025,
      "week": 2,
      "team": "SEA",
      "offense_snaps": 0.0,
      "defense_snaps": 6.0,
      "special_teams_snaps": 14.0
    },
    {
      "season": 2025,
      "week": 1,
      "team": "SEA",
      "offense_snaps": 0.0,
      "defense_snaps": 3.0,
      "special_teams_snaps": 13.0
    },
    {
      "season": 2024,
      "week": 18,
      "team": "SEA",
      "offense_snaps": 0.0,
      "defense_snaps": 3.0,
      "special_teams_snaps": 14.0
    },
    {
      "season": 2024,
      "week": 17,
      "team": "SEA",
      "offense_snaps": 0.0,
      "defense_snaps": 0.0,
      "special_teams_snaps": 12.0
    },
    {
      "season": 2024,
      "week": 16,
      "team": "SEA",
      "offense_snaps": 0.0,
      "defense_snaps": 0.0,
      "special_teams_snaps": 17.0
    },
    {
      "season": 2024,
      "week": 15,
      "team": "SEA",
      "offense_snaps": 0.0,
      "defense_snaps": 0.0,
      "special_teams_snaps": 14.0
    },
    {
      "season": 2024,
      "week": 14,
      "team": "SEA",
      "offense_snaps": 0.0,
      "defense_snaps": 0.0,
      "special_teams_snaps": 15.0
    },
    {
      "season": 2024,
      "week": 12,
      "team": "SEA",
      "offense_snaps": 0.0,
      "defense_snaps": 0.0,
      "special_teams_snaps": 16.0
    },
    {
      "season": 2024,
      "week": 11,
      "team": "SEA",
      "offense_snaps": 0.0,
      "defense_snaps": 0.0,
      "special_teams_snaps": 19.0
    },
    {
      "season": 2024,
      "week": 9,
      "team": "SEA",
      "offense_snaps": 0.0,
      "defense_snaps": 0.0,
      "special_teams_snaps": 22.0
    },
    {
      "season": 2024,
      "week": 7,
      "team": "SEA",
      "offense_snaps": 0.0,
      "defense_snaps": 10.0,
      "special_teams_snaps": 21.0
    },
    {
      "season": 2024,
      "week": 6,
      "team": "SEA",
      "offense_snaps": 0.0,
      "defense_snaps": 9.0,
      "special_teams_snaps": 26.0
    },
    {
      "season": 2024,
      "week": 5,
      "team": "SEA",
      "offense_snaps": 0.0,
      "defense_snaps": 13.0,
      "special_teams_snaps": 26.0
    },
    {
      "season": 2024,
      "week": 4,
      "team": "SEA",
      "offense_snaps": 0.0,
      "defense_snaps": 10.0,
      "special_teams_snaps": 17.0
    },
    {
      "season": 2024,
      "week": 3,
      "team": "SEA",
      "offense_snaps": 0.0,
      "defense_snaps": 14.0,
      "special_teams_snaps": 21.0
    },
    {
      "season": 2024,
      "week": 2,
      "team": "SEA",
      "offense_snaps": 0.0,
      "defense_snaps": 2.0,
      "special_teams_snaps": 26.0
    },
    {
      "season": 2024,
      "week": 1,
      "team": "SEA",
      "offense_snaps": 0.0,
      "defense_snaps": 9.0,
      "special_teams_snaps": 21.0
    },
    {
      "season": 2023,
      "week": 1,
      "team": "SEA",
      "offense_snaps": 0.0,
      "defense_snaps": 26.0,
      "special_teams_snaps": 8.0
    }
  ],
  "depth_chart_recent": [
    {
      "season": 2026.0,
      "team": "SEA",
      "depth_position": "Left Defensive End",
      "depth_rank": 3.0
    },
    {
      "season": 2026.0,
      "team": "SEA",
      "depth_position": "Left Defensive End",
      "depth_rank": 2.0
    },
    {
      "season": 2025.0,
      "team": "SEA",
      "depth_position": "Left Defensive End",
      "depth_rank": 1.0
    },
    {
      "season": 2025.0,
      "team": "SEA",
      "depth_position": "Right Defensive End",
      "depth_rank": 2.0
    },
    {
      "season": 2025.0,
      "team": "SEA",
      "depth_position": "Left Defensive End",
      "depth_rank": 2.0
    }
  ],
  "draft_combine": [
    {
      "draft_year": 2023.0,
      "team": "SEA",
      "school": "Michigan",
      "round": 5.0,
      "pick": 151.0,
      "height": "",
      "weight": "",
      "forty": ""
    },
    {
      "draft_year": 2002.0,
      "team": "SEA",
      "school": "Oregon",
      "round": 2.0,
      "pick": 54.0,
      "height": "",
      "weight": "",
      "forty": ""
    }
  ],
  "is_placeholder": false
}